wear_sdk/__init__.py
wear_sdk/client.py
wear_sdk/errors.py
wear_sdk/generated_models.py
wear_sdk/py.typed
wear_sdk/types.py
wear_sdk-0.1.0.dist-info/METADATA
wear_sdk-0.1.0.dist-info/WHEEL
wear_sdk-0.1.0.dist-info/RECORD
